irloader/__init__.py
irloader/__main__.py
irloader/irloader.py
irloader/main.py
irloader/settings.py
irloader/streamaudio.py
irloader/streamingtest.py
irloader/wavdata.py
irloader/effects/00_effect_example.py
irloader/effects/__init__.py
irloader/effects/ir_convolve.py
irloader/effects/ir_lfilter.py
irloader-0.1.0.dist-info/METADATA
irloader-0.1.0.dist-info/RECORD
irloader-0.1.0.dist-info/WHEEL
irloader-0.1.0.dist-info/entry_points.txt
irloader-0.1.0.dist-info/top_level.txt
